cryno/__init__.py
cryno-0.0.0.dist-info/LICENSE
cryno-0.0.0.dist-info/METADATA
cryno-0.0.0.dist-info/WHEEL
cryno-0.0.0.dist-info/top_level.txt
cryno-0.0.0.dist-info/RECORD
