Metadata-Version: 2.1
Name: cryno
Version: 0.0.0
Summary: A python image processing library
Author: Schkimansky
Author-email: <ahmadchawla1432@gmail.com>
Keywords: python,image,processing,data,image data,image processing,image processor,image manipulation,editor,image editor
Classifier: Development Status :: 1 - Planning
Classifier: Intended Audience :: Developers
Classifier: Programming Language :: Python :: 3
Classifier: Operating System :: Unix
Classifier: Operating System :: MacOS :: MacOS X
Classifier: Operating System :: Microsoft :: Windows
License-File: LICENSE
